test_pythonn_libbb/__init__.py
test_pythonn_libbb/test_file.py
test_pythonn_libbb-0.1.5.dist-info/METADATA
test_pythonn_libbb-0.1.5.dist-info/WHEEL
test_pythonn_libbb-0.1.5.dist-info/top_level.txt
test_pythonn_libbb-0.1.5.dist-info/RECORD
