Metadata-Version: 2.4
Name: test_pythonn_libbb
Version: 0.1.5
Summary: Testing, testing
Home-page: 
Author: 
Author-email: 
Classifier: Programming Language :: Python :: 3
Requires-Python: >=3.7
Requires-Dist: numpy
Dynamic: classifier
Dynamic: description
Dynamic: description-content-type
Dynamic: requires-dist
Dynamic: requires-python
Dynamic: summary
